slidespeak.py
mseep_slidespeak_mcp-0.0.4.dist-info/METADATA
mseep_slidespeak_mcp-0.0.4.dist-info/WHEEL
mseep_slidespeak_mcp-0.0.4.dist-info/top_level.txt
mseep_slidespeak_mcp-0.0.4.dist-info/RECORD
