Metadata-Version: 2.4
Name: mseep-slidespeak-mcp
Version: 0.0.4
Summary: Add your description here
Author-email: mseep <support@skydeck.ai>
Requires-Python: >=3.12
Requires-Dist: httpx>=0.28.1
Requires-Dist: mcp[cli]>=1.5.0
